networkxtra/__init__.py
networkxtra/algorithms/__init__.py
networkxtra/algorithms/components.py
networkxtra/convert/__init__.py
networkxtra/convert/geojsonl.py
networkxtra/drawing/__init__.py
networkxtra/drawing/cairo.py
networkxtra/functions/__init__.py
networkxtra/functions/graph.py
networkxtra/functions/leafs.py
networkxtra/layout/__init__.py
networkxtra/layout/bfs.py
networkxtra/layout/lgl.py
networkxtra/readwrite/__init__.py
networkxtra/readwrite/geojsonl.py
networkxtra/readwrite/lgl.py
networkxtra-1.0.1.dist-info/LICENSE
networkxtra-1.0.1.dist-info/METADATA
networkxtra-1.0.1.dist-info/WHEEL
networkxtra-1.0.1.dist-info/RECORD
